kajson/__init__.py
kajson/class_registry.py
kajson/class_registry_abstract.py
kajson/exceptions.py
kajson/json_decoder.py
kajson/json_encoder.py
kajson/kajson.py
kajson/kajson_manager.py
kajson/py.typed
kajson/singleton.py
kajson/pyproject.toml
kajson-0.3.0.dist-info/METADATA
kajson-0.3.0.dist-info/WHEEL
kajson-0.3.0.dist-info/licenses/LICENSE
kajson-0.3.0.dist-info/RECORD
