Metadata-Version: 2.4
Name: kajson
Version: 0.3.0
Summary: Powerful universal JSON encoder/decoder for Python objects with support for pydantic v2.
Project-URL: Homepage, https://github.com/pipelex/kajson
Project-URL: Repository, https://github.com/pipelex/kajson
Project-URL: Documentation, https://github.com/pipelex/kajson
Author-email: "Evotis S.A.S." <evotis@pipelex.com>
Maintainer-email: Pipelex staff <oss@pipelex.com>
License-Expression: Apache-2.0
License-File: LICENSE
Classifier: License :: OSI Approved :: Apache Software License
Classifier: Operating System :: OS Independent
Classifier: Programming Language :: Python :: 3
Classifier: Programming Language :: Python :: 3.9
Classifier: Programming Language :: Python :: 3.10
Classifier: Programming Language :: Python :: 3.11
Classifier: Programming Language :: Python :: 3.12
Requires-Python: >=3.9
Requires-Dist: pydantic>=2.10.6
Provides-Extra: dev
Requires-Dist: mypy>=1.11.2; extra == 'dev'
Requires-Dist: pyright==1.1.398; extra == 'dev'
Requires-Dist: pytest-cov>=6.1.1; extra == 'dev'
Requires-Dist: pytest-mock>=3.14.0; extra == 'dev'
Requires-Dist: pytest-sugar>=1.0.0; extra == 'dev'
Requires-Dist: pytest>=8.3.3; extra == 'dev'
Requires-Dist: ruff>=0.6.8; extra == 'dev'
Provides-Extra: docs
Requires-Dist: mkdocs-glightbox==0.4.0; extra == 'docs'
Requires-Dist: mkdocs-material==9.6.14; extra == 'docs'
Requires-Dist: mkdocs-meta-manager==1.1.0; extra == 'docs'
Requires-Dist: mkdocs==1.6.1; extra == 'docs'
